apparat/__init__.py
apparat/misc.py
apparat/py.typed
apparat-0.2.0.dist-info/METADATA
apparat-0.2.0.dist-info/WHEEL
apparat-0.2.0.dist-info/RECORD
