Metadata-Version: 2.1
Name: apparat
Version: 0.2.0
Summary: This is the machine description framework
Home-page: https://projects.om-office.de/frans/apparat.git
Author: Frans Fürst
Author-email: frans.fuerst+gitlab@protonmail.com
Requires-Python: >=3.10.4,<4
Classifier: Programming Language :: Python :: 3
Classifier: Programming Language :: Python :: 3.11
Classifier: Programming Language :: Python :: 3.12
Requires-Dist: asyncinotify (>=4.0,<5.0)
Project-URL: Repository, https://projects.om-office.de/frans/apparat.git
